silit/__init__.py
silit/commands.py
silit/templates/project/build.py
silit/templates/project/setup.py
silit/templates/project/silit.py
silit/templates/project/app/__init__.py
silit/templates/project/config/config.py
silit/templates/project/public/index.py
silit/templates/project/routes/web.py
silit_framework-0.0.1.dist-info/METADATA
silit_framework-0.0.1.dist-info/WHEEL
silit_framework-0.0.1.dist-info/entry_points.txt
silit_framework-0.0.1.dist-info/top_level.txt
silit_framework-0.0.1.dist-info/RECORD
