Metadata-Version: 2.1
Name: silit_framework
Version: 0.0.1
Summary: SILIT: Scalable Interface for Lightweight Integrated Tooling, Framework for creating desktop applications with MVC structure using Python. Now Under Development.
Home-page: https://github.com/jiilanTj/silitframework
Author: Jiilan Nashrulloh Tanjung
Author-email: jiilan3maret2008@gmail.com
Classifier: Programming Language :: Python :: 3
Classifier: License :: OSI Approved :: MIT License
Classifier: Operating System :: OS Independent
Requires-Python: >=3.6
Requires-Dist: flask
